flask_camp/README.md
flask_camp/__init__.py
flask_camp/__main__.py
flask_camp/_event.py
flask_camp/_extension.py
flask_camp/_utils.py
flask_camp/client.py
flask_camp/docker-compose.yml
flask_camp/exceptions.py
flask_camp/utils.py
flask_camp/_schemas/__init__.py
flask_camp/_schemas/action_with_comment.json
flask_camp/_schemas/add_new_version.json
flask_camp/_schemas/create_document.json
flask_camp/_schemas/create_user.json
flask_camp/_schemas/delete_tag.json
flask_camp/_schemas/login_user.json
flask_camp/_schemas/merge_documents.json
flask_camp/_schemas/modify_document.json
flask_camp/_schemas/modify_tag.json
flask_camp/_schemas/modify_user.json
flask_camp/_schemas/modify_version.json
flask_camp/_schemas/reset_password.json
flask_camp/_schemas/validate_email.json
flask_camp/_schemas/entities/comment.json
flask_camp/_schemas/entities/document.json
flask_camp/_schemas/entities/role.json
flask_camp/_schemas/entities/tag_name.json
flask_camp/_schemas/entities/token.json
flask_camp/_schemas/entities/user_name.json
flask_camp/_services/_database.py
flask_camp/_services/_memory_cache.py
flask_camp/_services/_security.py
flask_camp/_services/_send_mail.py
flask_camp/docker/Dockerfile
flask_camp/docker/haproxy.cfg
flask_camp/docker/init_db.sh
flask_camp/docker/nginx.conf
flask_camp/docker/start.sh
flask_camp/docker/uwsgi.ini
flask_camp/models/__init__.py
flask_camp/models/_base_model.py
flask_camp/models/_document.py
flask_camp/models/_log.py
flask_camp/models/_tag.py
flask_camp/models/_user.py
flask_camp/views/healthcheck.py
flask_camp/views/home.py
flask_camp/views/logs.py
flask_camp/views/account/current_user.py
flask_camp/views/account/email_validation.py
flask_camp/views/account/reset_password.py
flask_camp/views/account/user.py
flask_camp/views/account/user_login.py
flask_camp/views/account/users.py
flask_camp/views/content/document.py
flask_camp/views/content/documents.py
flask_camp/views/content/merge.py
flask_camp/views/content/tags.py
Flask_Camp-0.0.25.dist-info/LICENCE
Flask_Camp-0.0.25.dist-info/METADATA
Flask_Camp-0.0.25.dist-info/WHEEL
Flask_Camp-0.0.25.dist-info/entry_points.txt
Flask_Camp-0.0.25.dist-info/top_level.txt
Flask_Camp-0.0.25.dist-info/RECORD
