Metadata-Version: 2.1
Name: Flask-Camp
Version: 0.0.25
Summary: Full featured (but generic) headless API for wikis
Author-email: Charles de Beauchesne <charles.de.beauchesne@gmail.com>
Classifier: Programming Language :: Python :: 3
Classifier: Development Status :: 1 - Planning
Classifier: License :: OSI Approved :: MIT License
Classifier: Natural Language :: English
Classifier: Operating System :: OS Independent
Classifier: Programming Language :: Python :: 3.9
Classifier: Programming Language :: Python :: 3.10
Classifier: Programming Language :: Python :: 3.11
Classifier: Framework :: Flask
Classifier: Topic :: Internet :: WWW/HTTP :: Dynamic Content :: Wiki
Requires-Python: >=3.9
License-File: LICENCE
Requires-Dist: docopt (>=0.6.2)
Requires-Dist: Flask (>=2.2.2)
Requires-Dist: Flask-Limiter (>=2.6.2)
Requires-Dist: Flask-Login (>=0.6.2)
Requires-Dist: Flask-Mail (>=0.9.1)
Requires-Dist: Flask-SQLAlchemy (>=2.5.1)
Requires-Dist: jsonschema (>=4.16.0)
Requires-Dist: psycopg2-binary (>=2.9.3)
Requires-Dist: redis (>=4.3.4)
Requires-Dist: SQLAlchemy (>=1.4.40)
